def_result/Result.py
def_result/ResultDetail.py
def_result/ResultDetails/ErrorDetail.py
def_result/ResultDetails/Errors/BadRequestError.py
def_result/ResultDetails/Errors/ConflictError.py
def_result/ResultDetails/Errors/ExceptionError.py
def_result/ResultDetails/Errors/ForbiddenError.py
def_result/ResultDetails/Errors/InternalError.py
def_result/ResultDetails/Errors/NotFoundError.py
def_result/ResultDetails/Errors/UnauthorizedError.py
def_result/ResultDetails/Errors/ValidationError.py
def_result/ResultDetails/Errors/__init__.py
def_result/ResultDetails/Success/CreatedDetail.py
def_result/ResultDetails/Success/NotModifiedDetail.py
def_result/ResultDetails/Success/PartialContentDetail.py
def_result/ResultDetails/Success/__init__.py
def_result/ResultDetails/SuccessDetail.py
def_result/ResultDetails/__init__.py
def_result/__init__.py
def_result/decorator.py
def_result-1.0.1.dist-info/LICENSE
def_result-1.0.1.dist-info/METADATA
def_result-1.0.1.dist-info/WHEEL
def_result-1.0.1.dist-info/RECORD
