Metadata-Version: 2.1
Name: def-result
Version: 1.0.1
Summary: A functional error handling library for working with the results of a function to improve managing errors.
Home-page: https://github.com/Payadel/def_result
License: GPLV3
Keywords: functional programming,error handling,def,function
Author: Payadel
Author-email: payadelteam@gmail.com
Requires-Python: >=3.10,<4.0
Classifier: License :: Other/Proprietary License
Classifier: Programming Language :: Python :: 3
Classifier: Programming Language :: Python :: 3.10
Classifier: Programming Language :: Python :: 3.11
Project-URL: Repository, https://github.com/Payadel/def_result
